odoo/addons/sale_blanket_order_carrier/LICENSE
odoo/addons/sale_blanket_order_carrier/README.rst
odoo/addons/sale_blanket_order_carrier/__init__.py
odoo/addons/sale_blanket_order_carrier/__manifest__.py
odoo/addons/sale_blanket_order_carrier/i18n/de.po
odoo/addons/sale_blanket_order_carrier/images/screen.png
odoo/addons/sale_blanket_order_carrier/models/__init__.py
odoo/addons/sale_blanket_order_carrier/models/blanket_order.py
odoo/addons/sale_blanket_order_carrier/static/description/icon.png
odoo/addons/sale_blanket_order_carrier/static/description/index.html
odoo/addons/sale_blanket_order_carrier/tests/TEST_INSTRUCTIONS.rst
odoo/addons/sale_blanket_order_carrier/views/view_blanket_order_form.xml
odoo/addons/sale_blanket_order_carrier/views/view_order_form.xml
odoo/addons/sale_blanket_order_carrier/wizard/__init__.py
odoo/addons/sale_blanket_order_carrier/wizard/create_sale_orders.py
odoo_addon_sale_blanket_order_carrier-16.0.1.0.0.dist-info/METADATA
odoo_addon_sale_blanket_order_carrier-16.0.1.0.0.dist-info/WHEEL
odoo_addon_sale_blanket_order_carrier-16.0.1.0.0.dist-info/top_level.txt
odoo_addon_sale_blanket_order_carrier-16.0.1.0.0.dist-info/RECORD
